bseqgen/__init__.py
bseqgen/base.py
bseqgen/py.typed
bseqgen/random_seq.py
bseqgen-0.1.4.dist-info/METADATA
bseqgen-0.1.4.dist-info/WHEEL
bseqgen-0.1.4.dist-info/licenses/LICENSE
bseqgen-0.1.4.dist-info/RECORD
