Metadata-Version: 2.4
Name: bseqgen
Version: 0.1.4
Summary: Library for generating and working with binary sequences.
Project-URL: Homepage, https://github.com/bloopy-code/bseqgen
Project-URL: Repository, https://github.com/bloopy-code/bseqgen.git
Project-URL: Issues, https://github.com/bloopy-code/bseqgen/issues
Project-URL: Changelog, https://github.com/bloopy-code/bseqgen/blob/main/CHANGELOG.md
Author: bloopycode
License-File: LICENSE
Requires-Python: >=3.11
